hello_world/__init__.py
hello_world/command_line.py
intel_ai_safety-0.0.0.dist-info/LICENSE
intel_ai_safety-0.0.0.dist-info/METADATA
intel_ai_safety-0.0.0.dist-info/WHEEL
intel_ai_safety-0.0.0.dist-info/entry_points.txt
intel_ai_safety-0.0.0.dist-info/top_level.txt
intel_ai_safety-0.0.0.dist-info/RECORD
