Metadata-Version: 2.1
Name: intel-ai-safety
Version: 0.0.0
Summary: Explainable AI Tooling (XAI). XAI is used to discover and explain a model's prediction in a way that is interpretable to the user. Relevant information in the dataset, featureset, and model's algorithms are exposed.
Home-page: https://github.com/IntelAI/intel-xai-tools
Author: IntelAI
Author-email: intelai@intel.com
License: Apache-2.0 license
Keywords: machine-learning ai deep-learing tensorflow pytorch explainable-ai
Classifier: Development Status :: 3 - Alpha
Classifier: License :: OSI Approved :: MIT License
Classifier: Programming Language :: Python :: 3.5
Classifier: Programming Language :: Python :: 3.6
Classifier: Programming Language :: Python :: 3.7
Classifier: Programming Language :: Python :: 3.8
Classifier: Topic :: Text Processing :: Linguistic
License-File: LICENSE
